.AssertFalse.ceylon:?:com.redhat.ceylon.compiler.java.test.fordebug.trace.assertFalse_.main(java.lang.String[]):3:2a (aload_0)
.AssertFalse.ceylon:?:com.redhat.ceylon.compiler.java.test.fordebug.trace.assertFalse_.main(java.lang.String[]):4:b6 (invokevirtual)
.AssertFalse.ceylon:?:com.redhat.ceylon.compiler.java.test.fordebug.trace.assertFalse_.main(java.lang.String[]):7:b8 (invokestatic)
..AssertFalse.ceylon:2:com.redhat.ceylon.compiler.java.test.fordebug.trace.assertFalse_.assertFalse():0:14 (ldc2_w)
..AssertFalse.ceylon:3:com.redhat.ceylon.compiler.java.test.fordebug.trace.assertFalse_.assertFalse():4:bb (new)
..AssertFalse.ceylon:3:com.redhat.ceylon.compiler.java.test.fordebug.trace.assertFalse_.assertFalse():7:59 (dup)
..AssertFalse.ceylon:3:com.redhat.ceylon.compiler.java.test.fordebug.trace.assertFalse_.assertFalse():11:59 (dup)
..AssertFalse.ceylon:3:com.redhat.ceylon.compiler.java.test.fordebug.trace.assertFalse_.assertFalse():15:12 (ldc)
..AssertFalse.ceylon:3:com.redhat.ceylon.compiler.java.test.fordebug.trace.assertFalse_.assertFalse():20:b8 (invokestatic)
..AssertFalse.ceylon:3:com.redhat.ceylon.compiler.java.test.fordebug.trace.assertFalse_.assertFalse():23:b6 (invokevirtual)
..AssertFalse.ceylon:3:com.redhat.ceylon.compiler.java.test.fordebug.trace.assertFalse_.assertFalse():26:12 (ldc)
..AssertFalse.ceylon:3:com.redhat.ceylon.compiler.java.test.fordebug.trace.assertFalse_.assertFalse():31:12 (ldc)
..AssertFalse.ceylon:3:com.redhat.ceylon.compiler.java.test.fordebug.trace.assertFalse_.assertFalse():36:b6 (invokevirtual)
..AssertFalse.ceylon:3:com.redhat.ceylon.compiler.java.test.fordebug.trace.assertFalse_.assertFalse():39:b7 (invokespecial)
..AssertFalse.ceylon:3:com.redhat.ceylon.compiler.java.test.fordebug.trace.assertFalse_.assertFalse():42:bf (athrow)