.AssertFalse.ceylon:?:main(java.lang.String[]):3:2a (aload_0)
.AssertFalse.ceylon:?:main(java.lang.String[]):4:b6 (invokevirtual)
.AssertFalse.ceylon:?:main(java.lang.String[]):7:b8 (invokestatic)
..AssertFalse.ceylon:2:assertFalse():0:14 (ldc2_w)
..AssertFalse.ceylon:3:assertFalse():4:bb (new)
..AssertFalse.ceylon:3:assertFalse():7:59 (dup)
..AssertFalse.ceylon:3:assertFalse():11:59 (dup)
..AssertFalse.ceylon:3:assertFalse():15:12 (ldc)
..AssertFalse.ceylon:3:assertFalse():20:b8 (invokestatic)
..AssertFalse.ceylon:3:assertFalse():23:b6 (invokevirtual)
..AssertFalse.ceylon:3:assertFalse():26:12 (ldc)
..AssertFalse.ceylon:3:assertFalse():31:12 (ldc)
..AssertFalse.ceylon:3:assertFalse():36:b6 (invokevirtual)
..AssertFalse.ceylon:3:assertFalse():39:b7 (invokespecial)
..AssertFalse.ceylon:3:assertFalse():42:bf (athrow)