.Bug2047.ceylon:?:com.redhat.ceylon.compiler.java.test.fordebug.trace.bug2047_.main(java.lang.String[]):3:2a (aload_0)
.Bug2047.ceylon:?:com.redhat.ceylon.compiler.java.test.fordebug.trace.bug2047_.main(java.lang.String[]):4:b6 (invokevirtual)
.Bug2047.ceylon:?:com.redhat.ceylon.compiler.java.test.fordebug.trace.bug2047_.main(java.lang.String[]):7:b8 (invokestatic)
..Bug2047.ceylon:2:com.redhat.ceylon.compiler.java.test.fordebug.trace.bug2047_.bug2047():0:bb (new)
..Bug2047.ceylon:2:com.redhat.ceylon.compiler.java.test.fordebug.trace.bug2047_.bug2047():3:59 (dup)
..Bug2047.ceylon:2:com.redhat.ceylon.compiler.java.test.fordebug.trace.bug2047_.bug2047():10:06 (iconst_3)
..Bug2047.ceylon:2:com.redhat.ceylon.compiler.java.test.fordebug.trace.bug2047_.bug2047():14:59 (dup)
..Bug2047.ceylon:2:com.redhat.ceylon.compiler.java.test.fordebug.trace.bug2047_.bug2047():35:12 (ldc)
...Bug2047.ceylon:2:com.redhat.ceylon.compiler.java.test.fordebug.trace.bug2047_$1.<init>(com.redhat.ceylon.compiler.java.runtime.model.TypeDescriptor, com.redhat.ceylon.compiler.java.runtime.model.TypeDescriptor, java.lang.String, short):0:2a (aload_0)
...Bug2047.ceylon:2:com.redhat.ceylon.compiler.java.test.fordebug.trace.bug2047_$1.<init>(com.redhat.ceylon.compiler.java.runtime.model.TypeDescriptor, com.redhat.ceylon.compiler.java.runtime.model.TypeDescriptor, java.lang.String, short):9:b1 (return)
..Bug2047.ceylon:2:com.redhat.ceylon.compiler.java.test.fordebug.trace.bug2047_.bug2047():41:4b (astore_0)
..Bug2047.ceylon:7:com.redhat.ceylon.compiler.java.test.fordebug.trace.bug2047_.bug2047():42:2a (aload_0)
..Bug2047.ceylon:7:com.redhat.ceylon.compiler.java.test.fordebug.trace.bug2047_.bug2047():48:b9 (invokeinterface)
...Bug2047.ceylon:2:com.redhat.ceylon.compiler.java.test.fordebug.trace.bug2047_$1.$call$(java.lang.Object):0:2a (aload_0)
....Bug2047.ceylon:2:com.redhat.ceylon.compiler.java.test.fordebug.trace.bug2047_$1.$call$(java.lang.Object):0:2b (aload_1)
....Bug2047.ceylon:2:com.redhat.ceylon.compiler.java.test.fordebug.trace.bug2047_$1.$call$(java.lang.Object):7:4d (astore_2)
....Bug2047.ceylon:3:com.redhat.ceylon.compiler.java.test.fordebug.trace.bug2047_$1.$call$(java.lang.Object):8:2c (aload_2)
....Bug2047.ceylon:3:com.redhat.ceylon.compiler.java.test.fordebug.trace.bug2047_$1.$call$(java.lang.Object):12:b8 (invokestatic)
....Bug2047.ceylon:3:com.redhat.ceylon.compiler.java.test.fordebug.trace.bug2047_$1.$call$(java.lang.Object):15:b0 (areturn)
...Bug2047.ceylon:2:com.redhat.ceylon.compiler.java.test.fordebug.trace.bug2047_$1.$call$(java.lang.Object):5:b0 (areturn)
..Bug2047.ceylon:7:com.redhat.ceylon.compiler.java.test.fordebug.trace.bug2047_.bug2047():53:c0 (checkcast)
..Bug2047.ceylon:7:com.redhat.ceylon.compiler.java.test.fordebug.trace.bug2047_.bug2047():59:4c (astore_1)
..Bug2047.ceylon:1:com.redhat.ceylon.compiler.java.test.fordebug.trace.bug2047_.bug2047():60:b1 (return)
.Bug2047.ceylon:?:com.redhat.ceylon.compiler.java.test.fordebug.trace.bug2047_.main(java.lang.String[]):10:b1 (return)