.DefaultedParameters.ceylon:?:com.redhat.ceylon.compiler.java.test.fordebug.trace.defaultedParametersMain_.main(java.lang.String[]):3:2a (aload_0)
.DefaultedParameters.ceylon:?:com.redhat.ceylon.compiler.java.test.fordebug.trace.defaultedParametersMain_.main(java.lang.String[]):4:b6 (invokevirtual)
.DefaultedParameters.ceylon:?:com.redhat.ceylon.compiler.java.test.fordebug.trace.defaultedParametersMain_.main(java.lang.String[]):7:b8 (invokestatic)
..DefaultedParameters.ceylon:7:com.redhat.ceylon.compiler.java.test.fordebug.trace.defaultedParametersMain_.defaultedParametersMain():0:b8 (invokestatic)
...DefaultedParameters.ceylon:2:com.redhat.ceylon.compiler.java.test.fordebug.trace.defaultedParameters_.defaultedParameters():0:b8 (invokestatic)
....DefaultedParameters.ceylon:2:com.redhat.ceylon.compiler.java.test.fordebug.trace.defaultedParameters_.defaultedParameters$s():0:12 (ldc)
...DefaultedParameters.ceylon:2:com.redhat.ceylon.compiler.java.test.fordebug.trace.defaultedParameters_.defaultedParameters():3:4b (astore_0)
...DefaultedParameters.ceylon:3:com.redhat.ceylon.compiler.java.test.fordebug.trace.defaultedParameters_.defaultedParameters():4:2a (aload_0)
....DefaultedParameters.ceylon:3:com.redhat.ceylon.compiler.java.test.fordebug.trace.defaultedParameters_.defaultedParameters$i(java.lang.String):0:09 (lconst_0)
...DefaultedParameters.ceylon:3:com.redhat.ceylon.compiler.java.test.fordebug.trace.defaultedParameters_.defaultedParameters():8:40 (lstore_1)
....DefaultedParameters.ceylon:4:com.redhat.ceylon.compiler.java.test.fordebug.trace.defaultedParameters_.defaultedParameters(java.lang.String, long):0:1f (lload_1)
....DefaultedParameters.ceylon:4:com.redhat.ceylon.compiler.java.test.fordebug.trace.defaultedParameters_.defaultedParameters(java.lang.String, long):5:61 (ladd)
...DefaultedParameters.ceylon:3:com.redhat.ceylon.compiler.java.test.fordebug.trace.defaultedParameters_.defaultedParameters():14:ad (lreturn)
..DefaultedParameters.ceylon:7:com.redhat.ceylon.compiler.java.test.fordebug.trace.defaultedParametersMain_.defaultedParametersMain():3:58 (pop2)
..DefaultedParameters.ceylon:8:com.redhat.ceylon.compiler.java.test.fordebug.trace.defaultedParametersMain_.defaultedParametersMain():4:12 (ldc)
...DefaultedParameters.ceylon:3:com.redhat.ceylon.compiler.java.test.fordebug.trace.defaultedParameters_.defaultedParameters(java.lang.String):0:2a (aload_0)
....DefaultedParameters.ceylon:3:com.redhat.ceylon.compiler.java.test.fordebug.trace.defaultedParameters_.defaultedParameters$i(java.lang.String):0:09 (lconst_0)
...DefaultedParameters.ceylon:3:com.redhat.ceylon.compiler.java.test.fordebug.trace.defaultedParameters_.defaultedParameters(java.lang.String):4:40 (lstore_1)
....DefaultedParameters.ceylon:4:com.redhat.ceylon.compiler.java.test.fordebug.trace.defaultedParameters_.defaultedParameters(java.lang.String, long):0:1f (lload_1)
....DefaultedParameters.ceylon:4:com.redhat.ceylon.compiler.java.test.fordebug.trace.defaultedParameters_.defaultedParameters(java.lang.String, long):5:61 (ladd)
...DefaultedParameters.ceylon:3:com.redhat.ceylon.compiler.java.test.fordebug.trace.defaultedParameters_.defaultedParameters(java.lang.String):10:ad (lreturn)
..DefaultedParameters.ceylon:8:com.redhat.ceylon.compiler.java.test.fordebug.trace.defaultedParametersMain_.defaultedParametersMain():9:58 (pop2)
..DefaultedParameters.ceylon:10:com.redhat.ceylon.compiler.java.test.fordebug.trace.defaultedParametersMain_.defaultedParametersMain():10:0a (lconst_1)
..DefaultedParameters.ceylon:9:com.redhat.ceylon.compiler.java.test.fordebug.trace.defaultedParametersMain_.defaultedParametersMain():12:b8 (invokestatic)
...DefaultedParameters.ceylon:2:com.redhat.ceylon.compiler.java.test.fordebug.trace.defaultedParameters_.defaultedParameters$s():0:12 (ldc)
..DefaultedParameters.ceylon:9:com.redhat.ceylon.compiler.java.test.fordebug.trace.defaultedParametersMain_.defaultedParametersMain():15:4d (astore_2)
...DefaultedParameters.ceylon:4:com.redhat.ceylon.compiler.java.test.fordebug.trace.defaultedParameters_.defaultedParameters(java.lang.String, long):0:1f (lload_1)
...DefaultedParameters.ceylon:4:com.redhat.ceylon.compiler.java.test.fordebug.trace.defaultedParameters_.defaultedParameters(java.lang.String, long):5:61 (ladd)
..DefaultedParameters.ceylon:9:com.redhat.ceylon.compiler.java.test.fordebug.trace.defaultedParametersMain_.defaultedParametersMain():21:58 (pop2)
..DefaultedParameters.ceylon:6:com.redhat.ceylon.compiler.java.test.fordebug.trace.defaultedParametersMain_.defaultedParametersMain():22:b1 (return)
.DefaultedParameters.ceylon:?:com.redhat.ceylon.compiler.java.test.fordebug.trace.defaultedParametersMain_.main(java.lang.String[]):10:b1 (return)