.DefaultedParameters.ceylon:?:main(java.lang.String[]):3:2a (aload_0)
.DefaultedParameters.ceylon:?:main(java.lang.String[]):4:b6 (invokevirtual)
.DefaultedParameters.ceylon:?:main(java.lang.String[]):7:b8 (invokestatic)
..DefaultedParameters.ceylon:5:defaultedParametersMain():0:b8 (invokestatic)
....DefaultedParameters.ceylon:1:defaultedParameters$s():2:b0 (areturn)
...DefaultedParameters.ceylon:?:defaultedParameters():3:4b (astore_0)
...DefaultedParameters.ceylon:?:defaultedParameters():4:2a (aload_0)
...DefaultedParameters.ceylon:?:defaultedParameters():5:b8 (invokestatic)
....DefaultedParameters.ceylon:1:defaultedParameters$i(java.lang.String):0:09 (lconst_0)
...DefaultedParameters.ceylon:?:defaultedParameters():8:40 (lstore_1)
...DefaultedParameters.ceylon:?:defaultedParameters():9:2a (aload_0)
...DefaultedParameters.ceylon:?:defaultedParameters():10:1f (lload_1)
...DefaultedParameters.ceylon:?:defaultedParameters():11:b8 (invokestatic)
....DefaultedParameters.ceylon:2:defaultedParameters(java.lang.String, long):0:1f (lload_1)
....DefaultedParameters.ceylon:2:defaultedParameters(java.lang.String, long):5:61 (ladd)
...DefaultedParameters.ceylon:?:defaultedParameters():14:ad (lreturn)
..DefaultedParameters.ceylon:5:defaultedParametersMain():3:58 (pop2)
..DefaultedParameters.ceylon:6:defaultedParametersMain():4:12 (ldc)
....DefaultedParameters.ceylon:1:defaultedParameters$i(java.lang.String):1:ad (lreturn)
...DefaultedParameters.ceylon:?:defaultedParameters(java.lang.String):4:40 (lstore_1)
...DefaultedParameters.ceylon:?:defaultedParameters(java.lang.String):5:2a (aload_0)
...DefaultedParameters.ceylon:?:defaultedParameters(java.lang.String):6:1f (lload_1)
...DefaultedParameters.ceylon:?:defaultedParameters(java.lang.String):7:b8 (invokestatic)
....DefaultedParameters.ceylon:2:defaultedParameters(java.lang.String, long):0:1f (lload_1)
....DefaultedParameters.ceylon:2:defaultedParameters(java.lang.String, long):5:61 (ladd)
...DefaultedParameters.ceylon:?:defaultedParameters(java.lang.String):10:ad (lreturn)
..DefaultedParameters.ceylon:6:defaultedParametersMain():9:58 (pop2)
..DefaultedParameters.ceylon:8:defaultedParametersMain():10:0a (lconst_1)
..DefaultedParameters.ceylon:7:defaultedParametersMain():12:b8 (invokestatic)
...DefaultedParameters.ceylon:1:defaultedParameters$s():0:12 (ldc)
..DefaultedParameters.ceylon:7:defaultedParametersMain():15:4d (astore_2)
...DefaultedParameters.ceylon:2:defaultedParameters(java.lang.String, long):0:1f (lload_1)
...DefaultedParameters.ceylon:2:defaultedParameters(java.lang.String, long):5:61 (ladd)
..DefaultedParameters.ceylon:7:defaultedParametersMain():21:58 (pop2)
..DefaultedParameters.ceylon:4:defaultedParametersMain():22:b1 (return)
.DefaultedParameters.ceylon:?:main(java.lang.String[]):10:b1 (return)